{
	"properties": [
		{
			"description": "Data da requisição",
			"infoPropriedade": "DATA",
			"tipoValor": "DATA",
			"iis": "date",
			"apache": "%d",
			"nginx": "$d"
		},
		{
			"description": "Hora da requisição",
			"infoPropriedade": "HORA",
			"tipoValor": "HORA",
			"iis": "time",
			"apache": "%d",
			"nginx": "$d"
		},
		{
			"description": "URL",
			"infoPropriedade": "URL",
			"tipoValor": "STRING",
			"apache": "%u",
			"nginx": "$u",
			"iis": "cs-uri-stem"
		},
		{
			"description": "Porta",
			"infoPropriedade": "PORTA",
			"tipoValor": "NUMERICO",
			"apache": "%p",
			"nginx": "$p",
			"iis": "s-port"
		},
		{
			"description": "Tamanho",
			"infoPropriedade": "TAMANHO",
			"tipoValor": "NUMERICO",
			"apache": "%t",
			"nginx": "$t",
			"iis": "sc-bytes"
		},
		{
			"description": "Tempo total da requisição",
			"infoPropriedade": "TEMPO",
			"tipoValor": "NUMERICO",
			"apache": "%i",
			"nginx": "$i",
			"iis": "time-taken"
		},
		{
			"description": "Endereço IP do client que fez a requisição",
			"infoPropriedade": "CLIENT_IP",
			"tipoValor": "STRING",
			"apache": "%ci",
			"nginx": "$ci",
			"iis": "c-ip"
		},
		{
			"description": "Código da situação do Protocolo utilizado",
			"infoPropriedade": "PROTOCOL_STATUS",
			"tipoValor": "NUMERICO",
			"apache": "%casi",
			"nginx": "$casi",
			"iis": "sc-status"
		}
	]
}